{	"responseType": "GetServicesListRet",	"responseStatus": {		"success": "0",		"desc": "成功"	},	"responseContent": [{		"id": "1001243",		"site": "A01",		"type": "1",		"time": "2017-04-04 22:12:01",		"status": "0",		"desc": "测试数据"				},{		"id": "1001244",		"site": "A02",		"type": "1",		"time": "2017-04-04 22:12:01",		"status": "0",		"desc": "测试数据"				},{		"id": "1001245",		"site": "A04",		"type": "1",		"time": "2017-04-04 22:12:01",		"status": "0",		"desc": "测试数据"				}	,{		"id": "1001246",		"site": "B04",		"type": "1",		"time": "2017-04-04 22:12:01",		"status": "0",		"desc": "测试数据"				},{		"id": "1001247",		"site": "D02",		"type": "1",		"time": "2017-04-04 22:12:01",		"status": "0",		"desc": "测试数据"				},{		"id": "1001248",		"site": "C04",		"type": "1",		"time": "2017-04-04 22:12:01",		"status": "0",		"desc": "测试数据"				}	,{		"id": "1001249",		"site": "E04",		"type": "1",		"time": "2017-04-04 22:12:01",		"status": "0",		"desc": "测试数据"				}	]}